{
  "id": "post_1762817462676_fkzl9ycwo",
  "slug": "house-smells-like-cat-litter-solutions",
  "title": "¿Tu Casa Huele a Arena para Gatos? 7 Soluciones Probadas para Controlar el Olor a Arena para Gatos",
  "excerpt": "Detén los olores vergonzosos de la arena para gatos en 24 horas. 7 métodos probados para eliminar el olor de la caja de arena y mantener tu hogar fresco.",
  "content": "<div class=\"max-w-4xl mx-auto\">\n\n            <header class=\"mb-12 text-center dark:text-center\">\n              <div class=\"inline-block px-4 py-1 bg-[#E0EFC7] dark:bg-[#E0EFC7]/20 rounded-full text-[#FF3131] dark:text-[#FF6B6B] font-medium text-sm mb-4\">\n                Soluciones de Control de Olores\n              </div>\n              <h2 class=\"text-4xl md:text-5xl font-bold tracking-tight mb-6 text-gray-900 dark:text-gray-50\">\n                ¿Tu Casa Huele a Arena para Gatos? 7 Soluciones Probadas para Controlar el Olor a Arena para Gatos\n              </h2>\n              <p class=\"text-xl text-gray-600 dark:text-gray-300 max-w-3xl mx-auto\">\n                Detén los olores persistentes de la caja de arena que invaden tu hogar. Descubre métodos efectivos respaldados por la ciencia\n                para eliminar olores fuertes de orina y mantener tu casa fresca.\n              </p>\n              <div class=\"flex items-center justify-center space-x-4 mt-6 text-sm text-gray-500 dark:text-gray-400 dark:text-gray-500\">\n                <span>Publicado el 15 de diciembre de 2024</span>\n                <span>•</span>\n                <span>6 min de lectura</span>\n              </div>\n            </header>\n\n            <div class=\"prose prose-lg max-w-none dark:prose-invert\">\n              <p class=\"text-gray-700 dark:text-gray-200 mb-6 text-xl leading-relaxed\">\n                ¿Tu <strong>casa huele a arena para gatos</strong> sin importar con qué frecuencia limpies? No estás solo.\n                Muchos dueños de gatos luchan con olores persistentes de la caja de arena que parecen impregnar toda su casa.\n                La buena noticia es que con el enfoque correcto, puedes <strong>controlar el olor a arena para gatos</strong> de manera efectiva\n                y permanente.\n              </p>\n\n              <h2 class=\"text-3xl font-bold text-gray-900 dark:text-gray-50 mb-6\">¿Por Qué Mi Casa Huele a Arena para Gatos?</h2>\n\n              <p class=\"text-gray-700 dark:text-gray-200 mb-6\">\n                Cuando tu <strong>casa huele a arena para gatos</strong>, generalmente se debe a uno o más de estos problemas comunes:\n              </p>\n\n              <ul class=\"list-disc pl-6 mb-8 text-gray-700 dark:text-gray-200\">\n                <li><strong>Mantenimiento inadecuado de la caja de arena:</strong> La limpieza poco frecuente permite que los olores se acumulen</li>\n                <li><strong>Ventilación deficiente:</strong> El aire estancado atrapa moléculas de olor en tu espacio vital</li>\n                <li><strong>Control de olores insuficiente:</strong> La arena básica por sí sola puede no neutralizar el fuerte olor a orina</li>\n                <li><strong>Múltiples gatos:</strong> Más gatos significan más desechos y olores más fuertes</li>\n                <li><strong>Problemas médicos:</strong> Los problemas de salud pueden causar orina de olor más fuerte</li>\n              </ul>\n\n              <h2 class=\"text-3xl font-bold text-gray-900 dark:text-gray-50 mb-6\">7 Soluciones Probadas para Controlar el Olor a Arena para Gatos</h2>\n\n              <h3 class=\"text-2xl font-bold text-gray-900 dark:text-gray-50 mb-4\">1. Usar Aditivos de Carbón Activado para Arena</h3>\n\n              <p class=\"text-gray-700 dark:text-gray-200 mb-6\">\n                La forma más efectiva de eliminar el <strong>olor a orina de la arena para gatos</strong> es con aditivos de carbón activado.\n                A diferencia de los ambientadores que enmascaran los olores, el carbón activado realmente captura y atrapa las moléculas de olor en la fuente.\n              </p>\n\n              <div class=\"bg-green-50 dark:bg-green-900/20 border border-green-200 dark:border-green-700 rounded-lg p-6 mb-8\">\n                <h4 class=\"font-bold text-green-900 dark:text-green-100 mb-3\">🌟 Por Qué el Carbón Activado Funciona Mejor:</h4>\n                <ul class=\"text-green-800 dark:text-green-200 space-y-2\">\n                  <li>• Atrapa amoníaco y compuestos de azufre de la orina</li>\n                  <li>• Funciona hasta 7 días por aplicación</li>\n                  <li>• Sin fragancias artificiales ni químicos</li>\n                  <li>• Seguro para gatos y humanos</li>\n                </ul>\n              </div>\n\n              <h3 class=\"text-2xl font-bold text-gray-900 dark:text-gray-50 mb-4\">2. Mantener un Horario de Limpieza Adecuado de la Caja de Arena</h3>\n\n              <div class=\"mb-8\">\n                <img src=\"/optimized/blog/safe-cat-litter-ghibli.png\" alt=\"House Smells Like Cat Litter? 7 Proven Solutions to Control Cat Litter Smell\" class=\"w-full rounded-2xl shadow-lg mb-4\" />\n                <p class=\"text-sm text-gray-500 dark:text-gray-400 dark:text-gray-500 text-center mt-2\">\n                  La rutina de limpieza consistente es clave para la prevención de olores\n                </p>\n              </div>\n\n              <p class=\"text-gray-700 dark:text-gray-200 mb-6\">\n                Para prevenir el <strong>fuerte olor a orina en tu caja de arena para gatos</strong>, establece una rutina de limpieza consistente:\n              </p>\n\n              <ul class=\"list-disc pl-6 mb-6 text-gray-700 dark:text-gray-200\">\n                <li>Recoge los desechos diariamente (dos veces al día para múltiples gatos)</li>\n                <li>Cambia la arena completamente cada 1-2 semanas</li>\n                <li>Lava la caja de arena con jabón suave mensualmente</li>\n                <li>Reemplaza las cajas de arena viejas anualmente</li>\n              </ul>\n\n              <h3 class=\"text-2xl font-bold text-gray-900 dark:text-gray-50 mb-4\">3. Mejorar la Ventilación Alrededor del Área de Arena</h3>\n\n              <div class=\"mb-8\">\n                <img src=\"/optimized/blog/safe-cat-litter-ghibli.png\" alt=\"Proper ventilation for litter box area\" class=\"w-full rounded-2xl shadow-lg mb-4\" />\n                <p class=\"text-sm text-gray-500 dark:text-gray-400 dark:text-gray-500 text-center mt-2\">\n                  La ventilación adecuada ayuda a eliminar los olores naturalmente\n                </p>\n              </div>\n\n              <p class=\"text-gray-700 dark:text-gray-200 mb-6\">\n                Un buen flujo de aire es crucial para <strong>sacar el olor a arena para gatos de tu casa</strong>. Considera estas mejoras de ventilación:\n              </p>\n\n              <ul class=\"list-disc pl-6 mb-6 text-gray-700 dark:text-gray-200\">\n                <li>Instala un ventilador de extracción cerca de la caja de arena</li>\n                <li>Mantén las ventanas abiertas cuando sea posible</li>\n                <li>Usa purificadores de aire con filtros de carbón activado</li>\n                <li>Evita colocar cajas de arena en espacios cerrados</li>\n              </ul>\n\n              <h3 class=\"text-2xl font-bold text-gray-900 dark:text-gray-50 mb-4\">4. Elegir el Tipo Correcto de Arena</h3>\n\n              <p class=\"text-gray-700 dark:text-gray-200 mb-6\">\n                Algunas arenas son mejores para controlar los olores que otras. Busca:\n              </p>\n\n              <ul class=\"list-disc pl-6 mb-6 text-gray-700 dark:text-gray-200\">\n                <li>Arena de arcilla aglomerante para fácil eliminación de desechos</li>\n                <li>Opciones sin perfume (los gatos las prefieren)</li>\n                <li>Profundidad de arena de 5 a 8 cm para aglomeración óptima</li>\n                <li>Arena de alta calidad que controla el polvo</li>\n              </ul>\n\n              <h3 class=\"text-2xl font-bold text-gray-900 dark:text-gray-50 mb-4\">5. Abordar Hogares con Múltiples Gatos</h3>\n\n              <div class=\"mb-8\">\n                <img src=\"/optimized/blog/catonbed-ghibli.png\" alt=\"Multiple cats in a household\" class=\"w-full rounded-2xl shadow-lg mb-4\" />\n                <p class=\"text-sm text-gray-500 dark:text-gray-400 dark:text-gray-500 text-center mt-2\">\n                  Múltiples gatos requieren colocación y gestión estratégica de cajas de arena\n                </p>\n              </div>\n\n              <p class=\"text-gray-700 dark:text-gray-200 mb-6\">\n                Si tu <strong>casa huele a caja de arena</strong> debido a múltiples gatos, necesitas:\n              </p>\n\n              <ul class=\"list-disc pl-6 mb-6 text-gray-700 dark:text-gray-200\">\n                <li>Una caja de arena por gato, más una extra</li>\n                <li>Cajas colocadas en diferentes áreas de la casa</li>\n                <li>Limpieza más frecuente (mínimo dos veces al día)</li>\n                <li>Soluciones de control de olores más fuertes como el carbón activado</li>\n              </ul>\n\n              <h3 class=\"text-2xl font-bold text-gray-900 dark:text-gray-50 mb-4\">6. Monitorear la Salud de Tu Gato</h3>\n\n              <p class=\"text-gray-700 dark:text-gray-200 mb-6\">\n                Un <strong>olor a orina inusualmente fuerte de tu caja de arena para gatos</strong> podría indicar problemas de salud:\n              </p>\n\n              <ul class=\"list-disc pl-6 mb-6 text-gray-700 dark:text-gray-200\">\n                <li>Las infecciones del tracto urinario pueden causar olores más fuertes</li>\n                <li>La enfermedad renal afecta la concentración de orina</li>\n                <li>La diabetes puede cambiar el olor de la orina</li>\n                <li>Consulta a tu veterinario si los olores se vuelven repentinamente más fuertes</li>\n              </ul>\n\n              <h3 class=\"text-2xl font-bold text-gray-900 dark:text-gray-50 mb-4\">7. Hacer Limpieza Profunda de Áreas Afectadas</h3>\n\n              <p class=\"text-gray-700 dark:text-gray-200 mb-6\">\n                Si los olores han impregnado tu hogar, es posible que necesites hacer una limpieza profunda:\n              </p>\n\n              <ul class=\"list-disc pl-6 mb-6 text-gray-700 dark:text-gray-200\">\n                <li>Usa limpiadores enzimáticos en cualquier accidente fuera de la caja</li>\n                <li>Limpia paredes y zócalos cerca del área de arena</li>\n                <li>Lava o reemplaza artículos de tela que puedan haber absorbido olores</li>\n                <li>Considera limpieza profesional de alfombras si es necesario</li>\n              </ul>\n\n              <div class=\"bg-[#FF3131]/10 border border-[#FF3131]/20 rounded-lg p-6 mb-8\">\n                <h4 class=\"font-bold text-[#FF3131] dark:text-[#FF6B6B] mb-3\">💡 Consejo Profesional: La Solución Purrify</h4>\n                <p class=\"text-gray-700 dark:text-gray-200 mb-4\">\n                  Para el control de olores más efectivo, prueba el <strong>aditivo de carbón activado para arena Purrify</strong>.\n                  Simplemente espolvoréalo en tu caja de arena para eliminar los olores hasta por 7 días. Hecho de\n                  carbón de cáscara de coco premium, es la misma tecnología utilizada en filtros de agua y aire.\n                </p>\n                <a href=\"/products\">\n                  Prueba Purrify Sin Riesgo →\n                </a>\n              </div>\n\n              <h2 class=\"text-3xl font-bold text-gray-900 dark:text-gray-50 mb-6\">Prevenir Futuros Problemas de Olor</h2>\n\n              <p class=\"text-gray-700 dark:text-gray-200 mb-6\">\n                Una vez que hayas eliminado los olores existentes, mantén un hogar de olor fresco con estos hábitos:\n              </p>\n\n              <ul class=\"list-disc pl-6 mb-6 text-gray-700 dark:text-gray-200\">\n                <li>Apégate a tu rutina de limpieza diaria</li>\n                <li>Usa aditivos de carbón activado regularmente</li>\n                <li>Monitorea la salud y el comportamiento de tu gato</li>\n                <li>Reemplaza las cajas de arena cuando se vuelvan porosas</li>\n                <li>Mantén suministros de respaldo a mano</li>\n              </ul>\n\n              <h2 class=\"text-3xl font-bold text-gray-900 dark:text-gray-50 mb-6\">Conclusión</h2>\n\n              <p class=\"text-gray-700 dark:text-gray-200 mb-6\">\n                No tienes que vivir con una <strong>casa que huele a arena para gatos</strong>. Al combinar el mantenimiento adecuado\n                de la caja de arena con soluciones efectivas de control de olores como el carbón activado, puedes eliminar\n                incluso los olores más fuertes permanentemente. La clave es la consistencia y usar métodos probados que se dirijan a\n                los olores en su fuente en lugar de simplemente enmascararlos.\n              </p>\n\n              <p class=\"text-gray-700 dark:text-gray-200\">\n                ¿Listo para transformar la calidad del aire de tu hogar?\n                <a href=\"/products\"> Prueba el aditivo de carbón activado Purrify</a>\n                y experimenta la diferencia que el control científico de olores puede hacer.\n              </p>\n            </div>\n\n            <div class=\"mt-16 pt-8 border-t border-gray-200 dark:border-gray-600\">\n              \n            </div>\n          </div>",
  "author": {
    "name": "Equipo Purrify",
    "avatar": "/optimized/team/team-avatar.png"
  },
  "publishDate": "2024-12-15T08:00:00-05:00",
  "modifiedDate": "2025-11-10T23:31:02.676Z",
  "status": "published",
  "featuredImage": {
    "url": "/optimized/blog/safe-cat-litter-ghibli.png",
    "alt": "House Smells Like Cat Litter? 7 Proven Solutions to Control Cat Litter Smell",
    "width": 1200,
    "height": 800
  },
  "categories": [
    "Odor Control Solutions",
    "Odor Control"
  ],
  "tags": [
    "house smells like cat litter",
    "control cat litter smell",
    "cat litter urine smell",
    "strong urine smell cat litter box",
    "getting cat litter smell out of house",
    "house smells like litter box"
  ],
  "locale": "es",
  "translations": {},
  "seo": {
    "title": "Deja de Avergonzarte - 7 Formas de Eliminar el Olor a Arena para Gatos",
    "description": "¡No más disculpas a los invitados! Estos 7 métodos probados eliminan olores vergonzosos de arena para gatos en 24 horas. El carbón activado de grado filtro de agua destruye…",
    "keywords": [
      "house smells like cat litter",
      "control cat litter smell",
      "cat litter urine smell",
      "strong urine smell cat litter box",
      "getting cat litter smell out of house",
      "house smells like litter box",
      "house smells like cat litter solutions"
    ],
    "ogImage": "/optimized/blog/safe-cat-litter-ghibli.png",
    "canonical": "https://www.purrify.ca/blog/house-smells-like-cat-litter-solutions"
  },
  "readingTime": 5
}
