{
  "id": "post_1737387600001_winter",
  "slug": "cat-litter-smell-worse-winter",
  "title": "Why Cat Litter Smells Worse in Winter (And 5 Solutions That Don't Require Opening Windows)",
  "excerpt": "Closed windows trapping unbearable ammonia odors? You're not alone. Discover why winter makes cat litter smell worse and 5 proven solutions that work without freezing your home.",
  "content": "<div class=\"max-w-4xl mx-auto\">\n            <nav class=\"mb-8\">\n              <ol class=\"flex items-center space-x-2 text-sm text-gray-600 dark:text-gray-300\">\n                <li><a href=\"/\" class=\"hover:text-[#FF3131] dark:hover:text-[#FF6B6B]\">Home</a></li>\n                <li>/</li>\n                <li><a href=\"/blog\" class=\"hover:text-[#FF3131] dark:hover:text-[#FF6B6B]\">Blog</a></li>\n                <li>/</li>\n                <li class=\"text-[#FF3131] dark:text-[#FF6B6B]\">Winter Odor Solutions</li>\n              </ol>\n            </nav>\n\n            <header class=\"mb-12 text-center\">\n              <div class=\"inline-block px-4 py-1 bg-blue-100 dark:bg-blue-900/30 rounded-full text-blue-700 dark:text-blue-400 font-medium text-sm mb-4\">\n                Seasonal Odor Control\n              </div>\n              <h1 class=\"font-heading text-4xl md:text-5xl font-bold tracking-tight mb-6 text-gray-900 dark:text-gray-50\">\n                Why Cat Litter Smells Worse in Winter (And 5 Solutions That Don't Require Opening Windows)\n              </h1>\n              <p class=\"text-xl text-gray-600 dark:text-gray-300 max-w-3xl mx-auto\">\n                Closed windows trapping unbearable ammonia odors? You're not alone. Discover why winter makes cat litter smell worse and 5 proven solutions that work without freezing your home.\n              </p>\n            </header>\n\n            <div class=\"mb-12\">\n              <img src=\"/optimized/winter-fresh-cat.webp\" alt=\"Cat looking out snowy window while owner deals with winter litter box odor in closed home\" class=\"w-full h-auto rounded-2xl shadow-xl\" width=\"1600\" height=\"1067\" />\n              <p class=\"text-sm text-gray-500 dark:text-gray-400 dark:text-gray-500 dark:text-gray-400 dark:text-gray-500 text-center mt-2\">\n                Winter's closed windows create the perfect storm for trapped cat litter odors\n              </p>\n            </div>\n\n            <div class=\"bg-blue-50 dark:bg-blue-900/20 border border-blue-200 dark:border-blue-700 rounded-xl p-6 mb-12\">\n              <h2 class=\"font-heading text-2xl font-bold text-blue-900 dark:text-blue-200 mb-4\">Quick Summary</h2>\n              <ul class=\"space-y-3 text-blue-800 dark:text-blue-300\">\n                <li><span class=\"mr-2\">❄️</span><strong>The Problem:</strong> Closed winter windows trap ammonia molecules that would normally escape, causing 3-5x odor concentration indoors.</li>\n                <li><span class=\"mr-2\">🔬</span><strong>The Science:</strong> Modern energy-efficient homes exchange air only 0.35 times per hour (ACH)—causing ammonia to concentrate up to 500% higher than summer levels.</li>\n                <li><span class=\"mr-2\">✅</span><strong>The Solution:</strong> Trap odors at the source with activated carbon, increase cleaning frequency, and optimize indoor air circulation.</li>\n              </ul>\n            </div>\n\n            <div class=\"prose prose-lg max-w-none\">\n              <h2 class=\"font-heading text-3xl font-bold text-gray-900 dark:text-gray-50 mb-6 mt-12\">The Winter Litter Box Problem Nobody Talks About</h2>\n\n              <p class=\"text-gray-700 dark:text-gray-200 mb-6 text-lg leading-relaxed\">\n                You've probably noticed it: the exact same litter box that was manageable in summer suddenly becomes overwhelming in winter. You walk into your home and hit a wall of ammonia smell. Your guests notice the second they walk through the door. Even your cat seems hesitant to use the box.\n              </p>\n\n              <h2 class=\"font-heading text-3xl font-bold text-gray-900 dark:text-gray-50 mb-6 mt-12\">Why Winter Is Different: The Science Behind Trapped Odors</h2>\n\n              <div class=\"mb-12\">\n                <img src=\"/optimized/frosted-winter-window.webp\" alt=\"Closed window with frost showing how winter weather keeps ammonia odors trapped indoors\" class=\"w-full h-auto rounded-xl shadow-lg\" width=\"1600\" height=\"1067\" />\n                <p class=\"text-sm text-gray-500 dark:text-gray-400 dark:text-gray-500 dark:text-gray-400 dark:text-gray-500 text-center mt-2\">\n                  Closed windows and sealed homes trap odor molecules that would normally escape\n                </p>\n              </div>\n\n              <h2 class=\"font-heading text-3xl font-bold text-gray-900 dark:text-gray-50 mb-6 mt-12\">5 Proven Solutions for Winter Cat Litter Odor</h2>\n\n              <div class=\"space-y-8 mb-12\">\n                <div class=\"bg-white dark:bg-gray-800 rounded-xl p-6 shadow-lg border border-[#E0EFC7] dark:border-gray-700\">\n                  <div class=\"flex items-start mb-4\">\n                    <div class=\"bg-[#5B2EFF] text-white rounded-full w-10 h-10 flex items-center justify-center font-bold text-xl mr-4 flex-shrink-0\">1</div>\n                    <div>\n                      <h3 class=\"font-heading text-2xl font-bold text-gray-900 dark:text-white mb-3\">Trap Odors at the Source with Activated Carbon</h3>\n                      <p class=\"text-gray-700 dark:text-gray-200 mb-4\">The most effective winter solution is preventing odors from entering your air in the first place. Activated carbon works through <em>adsorption</em>—millions of microscopic pores trap ammonia molecules before they can escape the litter box.</p>\n                    </div>\n                  </div>\n                </div>\n\n                <div class=\"bg-white dark:bg-gray-800 rounded-xl p-6 shadow-lg border border-[#E0EFC7] dark:border-gray-700\">\n                  <div class=\"flex items-start mb-4\">\n                    <div class=\"bg-[#5B2EFF] text-white rounded-full w-10 h-10 flex items-center justify-center font-bold text-xl mr-4 flex-shrink-0\">2</div>\n                    <div>\n                      <h3 class=\"font-heading text-2xl font-bold text-gray-900 dark:text-white mb-3\">Increase Cleaning Frequency by 25-50%</h3>\n                      <p class=\"text-gray-700 dark:text-gray-200 mb-4\">With reduced natural ventilation, waste accumulates faster in your indoor air. Adjust your schedule to scoop 2-3x daily.</p>\n                    </div>\n                  </div>\n                </div>\n\n                <div class=\"bg-white dark:bg-gray-800 rounded-xl p-6 shadow-lg border border-[#E0EFC7] dark:border-gray-700\">\n                  <div class=\"flex items-start mb-4\">\n                    <div class=\"bg-[#5B2EFF] text-white rounded-full w-10 h-10 flex items-center justify-center font-bold text-xl mr-4 flex-shrink-0\">3</div>\n                    <div>\n                      <h3 class=\"font-heading text-2xl font-bold text-gray-900 dark:text-white mb-3\">Optimize Indoor Air Circulation</h3>\n                      <p class=\"text-gray-700 dark:text-gray-200 mb-4\">Close vents near litter box, use exhaust fans after scooping, and add air purifiers with carbon filters.</p>\n                    </div>\n                  </div>\n                </div>\n\n                <div class=\"bg-white dark:bg-gray-800 rounded-xl p-6 shadow-lg border border-[#E0EFC7] dark:border-gray-700\">\n                  <div class=\"flex items-start mb-4\">\n                    <div class=\"bg-[#5B2EFF] text-white rounded-full w-10 h-10 flex items-center justify-center font-bold text-xl mr-4 flex-shrink-0\">4</div>\n                    <div>\n                      <h3 class=\"font-heading text-2xl font-bold text-gray-900 dark:text-white mb-3\">Switch to Low-Dust Litter</h3>\n                      <p class=\"text-gray-700 dark:text-gray-200 mb-4\">Winter's dry air exacerbates dust problems. Consider large-grain clumping clay, crystal/silica, or wood pellets.</p>\n                    </div>\n                  </div>\n                </div>\n\n                <div class=\"bg-white dark:bg-gray-800 rounded-xl p-6 shadow-lg border border-[#E0EFC7] dark:border-gray-700\">\n                  <div class=\"flex items-start mb-4\">\n                    <div class=\"bg-[#5B2EFF] text-white rounded-full w-10 h-10 flex items-center justify-center font-bold text-xl mr-4 flex-shrink-0\">5</div>\n                    <div>\n                      <h3 class=\"font-heading text-2xl font-bold text-gray-900 dark:text-white mb-3\">Consider a Covered Litter Box with Filter</h3>\n                      <p class=\"text-gray-700 dark:text-gray-200 mb-4\">Covered boxes with activated carbon filters contain odors before they escape—especially important when windows are closed.</p>\n                    </div>\n                  </div>\n                </div>\n              </div>\n\n              <div class=\"bg-gradient-to-r from-green-50 to-emerald-50 border border-green-200 dark:border-green-700 rounded-xl p-8 md:p-12 text-center my-12\">\n                <h2 class=\"font-heading text-3xl md:text-4xl font-bold text-green-900 dark:text-green-100 mb-6\">The Free Science Experiment</h2>\n                <p class=\"text-xl text-green-800 dark:text-green-200 mb-8 max-w-2xl mx-auto\">\n                  Still skeptical? Try our <strong>trial bag</strong> for free (just pay $4.76 shipping).\n                  If you don't notice the difference the <em>first day</em> you use it, we'll refund your shipping cost.\n                </p>\n                <a href=\"/products/trial-size\">\n                  <button class=\"bg-[#FF3131] hover:bg-[#E62E2E] text-white px-8 py-4 rounded-lg font-bold text-lg transition-all shadow-lg hover:shadow-xl transform hover:-translate-y-1\">\n                    Get Your Free Trial\n                  </button>\n                </a>\n              </div>\n            </div>\n          </div>",
  "author": {
    "name": "Purrify Team",
    "avatar": "/optimized/team-avatar.png"
  },
  "publishDate": "2025-01-20",
  "modifiedDate": "2025-01-20T12:00:00.000Z",
  "status": "published",
  "featuredImage": {
    "url": "/optimized/winter-fresh-cat.webp",
    "alt": "Cat looking out snowy window while owner deals with winter litter box odor in closed home",
    "width": 1600,
    "height": 1067
  },
  "categories": [
    "Seasonal Odor Control"
  ],
  "tags": [
    "cat litter smell winter",
    "closed windows litter box odor",
    "winter cat smell solutions",
    "ammonia smell worse in winter",
    "cat odor cold weather"
  ],
  "locale": "en",
  "translations": {},
  "seo": {
    "title": "Why Cat Litter Smells Worse in Winter (5 Solutions) | Purrify",
    "description": "Cat litter smell unbearable in winter? Closed windows trap ammonia odors. Discover 5 proven solutions that work without opening windows in cold weather.",
    "keywords": [
      "cat litter smell winter",
      "closed windows litter box odor",
      "winter cat smell solutions",
      "ammonia smell worse in winter",
      "cat odor cold weather"
    ],
    "canonical": "https://www.purrify.ca/blog/cat-litter-smell-worse-winter",
    "ogImage": "/optimized/winter-fresh-cat.webp"
  },
  "readingTime": 7
}
